README.md
setup.py
mkdocs_git_committers_plugin_cn/__init__.py
mkdocs_git_committers_plugin_cn/plugin.py
mkdocs_git_committers_plugin_cn.egg-info/PKG-INFO
mkdocs_git_committers_plugin_cn.egg-info/SOURCES.txt
mkdocs_git_committers_plugin_cn.egg-info/dependency_links.txt
mkdocs_git_committers_plugin_cn.egg-info/entry_points.txt
mkdocs_git_committers_plugin_cn.egg-info/requires.txt
mkdocs_git_committers_plugin_cn.egg-info/top_level.txt