Metadata-Version: 1.2
Name: mkdocs-git-committers-plugin-cn
Version: 0.1.0
Summary: An MkDocs plugin to create a list of contributors on the page
Home-page: https://github.com/zzzhxxx/mkdocs-git-committers-plugin-cn/
Author: Byrne Reese, Olivier Jacques, zzzhxxx
Author-email: byrne@majordojo.com, ojacques2@gmail.com,zhxsend@gmail.com
License: MIT
Keywords: mkdocs pdf github
Platform: UNKNOWN
Classifier: Development Status :: 4 - Beta
Classifier: Intended Audience :: Developers
Classifier: Intended Audience :: Information Technology
Classifier: License :: OSI Approved :: MIT License
Classifier: Programming Language :: Python
Classifier: Programming Language :: Python :: 3 :: Only
Classifier: Programming Language :: Python :: 3.4
Classifier: Programming Language :: Python :: 3.5
Classifier: Programming Language :: Python :: 3.6
Classifier: Programming Language :: Python :: 3.7
Requires-Python: >=2.7
